<mapping xmlns="http://www.iringtools.org/mapping" xmlns:i="http://www.w3.org/2001/XMLSchema-instance">
  <graphMaps>
    <graphMap>
      <name>Lines</name>
      <classTemplateMaps>
        <classTemplateMap>
          <classMap>
            <id>rdl:R19192462550</id>
            <name>PIPING NETWORK SYSTEM</name>
            <identifiers>
              <identifier>EQUIPMENT.TAG</identifier>
            </identifiers>
          </classMap>
          <templateMaps>
            <templateMap>
              <type>Definition</type>
              <id>tpl:tpl:R30193386273</id>
              <name>ClassifiedIdentification</name>
              <roleMaps>
                <roleMap>
                  <type>ObjectProperty</type>
                  <id>tpL:R30790108016</id>
                  <name>hasIdentificationType</name>
                  <dataType>
                    dm:ClassOfClassOfIdentification
                  </dataType>
                  <propertyName/>
                </roleMap>
                <roleMap>
                  <type>ObjectProperty</type>
                  <id>tpL:R44537504070</id>
                  <name>hasObject</name>
                  <dataType>dm:Thing</dataType>
                  <propertyName/>
                </roleMap>
                <roleMap>
                  <type>ObjectProperty</type>
                  <id>tpL:R22674749688</id>
                  <name>valIdentifier</name>
                  <dataType>xsd:string</dataType>
                  <propertyName/>
                </roleMap>
              </roleMaps>
            </templateMap>
          </templateMaps>
        </classTemplateMap>
      </classTemplateMaps>
      <dataObjectName>EQUIPMENT</dataObjectName>
    </graphMap>
  </graphMaps>
  <valueListMaps>
    <valueListMap>
      <name>Length</name>
      <valueMaps/>
    </valueListMap>
  </valueListMaps>
</mapping>